plemmy/__init__.py
plemmy/lemmyhttp.py
plemmy/objects.py
plemmy/responses.py
plemmy/types.py
plemmy/utils.py
plemmy/version.py
plemmy/views.py
tests/test_import.py
tests/test_lemmyhttp.py
plemmy-0.4.8.dist-info/LICENSE
plemmy-0.4.8.dist-info/METADATA
plemmy-0.4.8.dist-info/WHEEL
plemmy-0.4.8.dist-info/top_level.txt
plemmy-0.4.8.dist-info/RECORD
